app/__init__.py
mahmudhakker-0.0.1.dist-info/METADATA
mahmudhakker-0.0.1.dist-info/WHEEL
mahmudhakker-0.0.1.dist-info/top_level.txt
mahmudhakker-0.0.1.dist-info/RECORD
