Metadata-Version: 2.1
Name: mahmudhakker
Version: 0.0.1
Summary: Makhmud Library
Author: ozodbeksobirjonovich
Author-email: ozodbeksobirjonovich@gmail.com
Classifier: Programming Language :: Python :: 3
Classifier: License :: OSI Approved :: MIT License
Classifier: Operating System :: OS Independent
Requires-Python: >=3.6
